executor/engine/__init__.py
executor/engine/base.py
executor/engine/core.py
executor/engine/log.py
executor/engine/manager.py
executor/engine/utils.py
executor/engine/job/__init__.py
executor/engine/job/base.py
executor/engine/job/condition.py
executor/engine/job/dask.py
executor/engine/job/local.py
executor/engine/job/process.py
executor/engine/job/thread.py
executor/engine/job/utils.py
executor/engine/job/extend/__init__.py
executor/engine/job/extend/cron.py
executor/engine/job/extend/sentinel.py
executor/engine/job/extend/subprocess.py
executor/engine/job/extend/webapp.py
executor/engine/launcher/__init__.py
executor/engine/launcher/core.py
executor/engine/middle/__init__.py
executor/engine/middle/capture.py
executor/engine/middle/dir.py
executor_engine-0.3.3.dist-info/licenses/LICENSE
executor_engine-0.3.3.dist-info/METADATA
executor_engine-0.3.3.dist-info/WHEEL
executor_engine-0.3.3.dist-info/top_level.txt
executor_engine-0.3.3.dist-info/RECORD
