Metadata-Version: 2.4
Name: executor-engine
Version: 0.3.3
Summary: Package for manage job executions.
Home-page: https://github.com/Nanguage/executor-engine
Author: Weize Xu
Author-email: vet.xwz@gmail.com
License: MIT
Keywords: Job Management
Classifier: Development Status :: 3 - Alpha
Classifier: Operating System :: OS Independent
Classifier: Programming Language :: Python
Classifier: Programming Language :: Python :: 3
Classifier: Programming Language :: Python :: 3.8
Classifier: Programming Language :: Python :: 3.9
Classifier: Programming Language :: Python :: 3.10
Classifier: License :: OSI Approved :: MIT License
Classifier: Intended Audience :: Science/Research
Classifier: Intended Audience :: Developers
Requires-Python: >=3.8, <4
License-File: LICENSE
Requires-Dist: cmd2func>=0.1.9
Requires-Dist: funcdesc>=0.1.2
Requires-Dist: loky
Requires-Dist: diskcache
Requires-Dist: cloudpickle
Requires-Dist: psutil
Requires-Dist: loguru
Provides-Extra: dev
Requires-Dist: pip; extra == "dev"
Requires-Dist: setuptools; extra == "dev"
Requires-Dist: wheel; extra == "dev"
Requires-Dist: twine; extra == "dev"
Requires-Dist: ipdb; extra == "dev"
Requires-Dist: pytest; extra == "dev"
Requires-Dist: pytest-cov; extra == "dev"
Requires-Dist: pytest-asyncio; extra == "dev"
Requires-Dist: flake8; extra == "dev"
Requires-Dist: mypy; extra == "dev"
Requires-Dist: mkdocs; extra == "dev"
Requires-Dist: mkdocs-material; extra == "dev"
Requires-Dist: mkdocstrings[python]; extra == "dev"
Requires-Dist: mkdocs-autorefs; extra == "dev"
Requires-Dist: dask; extra == "dev"
Requires-Dist: distributed; extra == "dev"
Requires-Dist: nest_asyncio; extra == "dev"
Provides-Extra: dask
Requires-Dist: dask; extra == "dask"
Requires-Dist: distributed; extra == "dask"
Requires-Dist: nest_asyncio; extra == "dask"
Provides-Extra: all
Requires-Dist: dask; extra == "all"
Requires-Dist: distributed; extra == "all"
Requires-Dist: nest_asyncio; extra == "all"
Dynamic: author
Dynamic: author-email
Dynamic: classifier
Dynamic: description
Dynamic: home-page
Dynamic: keywords
Dynamic: license
Dynamic: license-file
Dynamic: provides-extra
Dynamic: requires-dist
Dynamic: requires-python
Dynamic: summary
